WinPkg_Installer/WinInstaller.py
WinPkg_Installer/__init__.py
WinInstaller-1.0.1.dist-info/LICENSE
WinInstaller-1.0.1.dist-info/METADATA
WinInstaller-1.0.1.dist-info/WHEEL
WinInstaller-1.0.1.dist-info/entry_points.txt
WinInstaller-1.0.1.dist-info/top_level.txt
WinInstaller-1.0.1.dist-info/RECORD
