Metadata-Version: 2.1
Name: WinInstaller
Version: 1.0.1
Summary: This package let's windows users to downlaod and install .zip or anyother files including adding the path to the Enviornmental Variables bychanging the PATH variable
Home-page: https://github.com/BuddhiD-Workaholic/WinPkg_Installer.git
Author: Buddhi Dhananjaya
Author-email: buddhi_dhananjaya@outlook.com
License: MIT
Keywords: WinInstaller WinInstaller WindowsPkg Windowspackagemanager package manager python package Windows Installer
Platform: UNKNOWN
Classifier: Programming Language :: Python :: 3
Classifier: License :: OSI Approved :: MIT License
Classifier: Operating System :: Microsoft :: Windows
